{
  "@odata.etag": "W/\"CQAAABYAAAApi2IKuXg2QJZLIBw8EBXsAAeVg/BN\"",
  "id": "AAMkAGYzNzQ3NThhLWVkOGQtNDJlMC1iYzBkLWFmZGRhMWI4NjRlYQBGAAAAAAAIJ8Vu3g_rSI1rdfqP2WW7BwApi2IKuXg2QJZLIBw8EBXsAAAAAAFQAAApi2IKuXg2QJZLIBw8EBXsAAWOmgiWAAA=",
  "receivedDateTime": "2025-09-01T16:01:54Z",
  "subject": "RE: הצעת מחיר לטיפול משפטי - רני דבוש (חב' RDP)",
  "bodyPreview": "הי איתן,\r\n\r\nמאושר להתקדם\r\n\r\n\r\nבברכה,\r\nרני דבוש\r\n052-2038055\r\n        https://www.rdpri.com/\r\n\r\n\r\nFrom: Rani Dabush\r\nSent: Monday, 1 September 2025 13:37\r\nTo: Eitan Shamir <eitan@eislaw.co.il>\r\nCc: Yael Shamir <yael@eislaw.co.il>; Alex Avramov <alex@rdpri.",
  "conversationId": "AAQkAGYzNzQ3NThhLWVkOGQtNDJlMC1iYzBkLWFmZGRhMWI4NjRlYQAQAK0HZKim_0tNkbxx9jJW2iQ=",
  "sender": {
    "emailAddress": {
      "name": "Rani Dabush",
      "address": "rani@rdpri.com"
    }
  },
  "from": {
    "emailAddress": {
      "name": "Rani Dabush",
      "address": "rani@rdpri.com"
    }
  },
  "toRecipients": [
    {
      "emailAddress": {
        "name": "Eitan Shamir",
        "address": "eitan@eislaw.co.il"
      }
    }
  ],
  "ccRecipients": [
    {
      "emailAddress": {
        "name": "Yael Shamir",
        "address": "yael@eislaw.co.il"
      }
    },
    {
      "emailAddress": {
        "name": "Alex Avramov",
        "address": "alex@rdpri.com"
      }
    }
  ],
  "replyTo": []
}