{
  "@odata.etag": "W/\"CQAAABYAAAApi2IKuXg2QJZLIBw8EBXsAAeWeyQG\"",
  "id": "AAMkAGYzNzQ3NThhLWVkOGQtNDJlMC1iYzBkLWFmZGRhMWI4NjRlYQBGAAAAAAAIJ8Vu3g_rSI1rdfqP2WW7BwApi2IKuXg2QJZLIBw8EBXsAAAAAAElAAApi2IKuXg2QJZLIBw8EBXsAAean27jAAA=",
  "receivedDateTime": "2025-10-21T06:29:25Z",
  "subject": "כתבה חדשה בנושא משפחה",
  "bodyPreview": "כשבתי המתבגרת הבינה שלא אחיה עד החתונה שלה, היא ביקשה שנקנה שמלת כלה\r\n\r\n\r\n\r\n\r\nמשפחה\r\n\r\nכשבתי המתבגרת הבינה שלא אחיה עד החתונה שלה, היא ביקשה שנקנה שמלת כלה\r\n\r\n\r\n\r\nלהמשך הכתבה\r\n\r\n\r\nכתבות שאולי פספסת\r\n\r\n\r\n\r\nגל הירש פתח את נאומו ב-4 מילים שלא נאמרו עד כה על ",
  "conversationId": "AAQkAGYzNzQ3NThhLWVkOGQtNDJlMC1iYzBkLWFmZGRhMWI4NjRlYQAQAH4ZImpZcqlEjLcWYmZuEmU=",
  "sender": {
    "emailAddress": {
      "name": "הארץ",
      "address": "sysadmin@mc.haaretz.com"
    }
  },
  "from": {
    "emailAddress": {
      "name": "הארץ",
      "address": "sysadmin@mc.haaretz.com"
    }
  },
  "toRecipients": [
    {
      "emailAddress": {
        "name": "Eitan Shamir",
        "address": "eitan@eislaw.co.il"
      }
    }
  ],
  "ccRecipients": [],
  "replyTo": []
}