{
  "@odata.etag": "W/\"CQAAABYAAAApi2IKuXg2QJZLIBw8EBXsAAdrDyQl\"",
  "id": "AAMkAGYzNzQ3NThhLWVkOGQtNDJlMC1iYzBkLWFmZGRhMWI4NjRlYQBGAAAAAAAIJ8Vu3g_rSI1rdfqP2WW7BwApi2IKuXg2QJZLIBw8EBXsAAAAAAEMAAApi2IKuXg2QJZLIBw8EBXsAAdvCWIMAAA=",
  "receivedDateTime": "2025-08-16T13:04:36Z",
  "subject": "Frank Dropped $1200 on Bourbon To Secure USAR Investment Banking Deal [True Story]",
  "bodyPreview": "Last week, a big-name research company you may recognize dropped a \"groundbreaking analysis\" telling subscribers to buy USA Rare Earth (NASDAQ: USAR) for potential 18,000% gains. ͏  ͏  ͏  ͏  ͏  ͏  ͏  ͏  ͏  ͏  ͏  ͏  ͏  ͏  ͏  ͏  ͏  ͏  ͏  ͏  ͏  ͏  ͏  ͏  ͏  ͏",
  "conversationId": "AAQkAGYzNzQ3NThhLWVkOGQtNDJlMC1iYzBkLWFmZGRhMWI4NjRlYQAQAEMtr93d8jdKiEqzpyfBzmE=",
  "sender": {
    "emailAddress": {
      "name": "Mark Sebastian",
      "address": "support@op.optionpit.com"
    }
  },
  "from": {
    "emailAddress": {
      "name": "Mark Sebastian",
      "address": "support@op.optionpit.com"
    }
  },
  "toRecipients": [
    {
      "emailAddress": {
        "name": "Eitan Shamir",
        "address": "eitan@eislaw.co.il"
      }
    }
  ],
  "ccRecipients": [],
  "replyTo": [
    {
      "emailAddress": {
        "name": "Mark Sebastian",
        "address": "support@op.optionpit.com"
      }
    }
  ]
}