{
  "@odata.etag": "W/\"CQAAABYAAAApi2IKuXg2QJZLIBw8EBXsAAd6kYvh\"",
  "id": "AAMkAGYzNzQ3NThhLWVkOGQtNDJlMC1iYzBkLWFmZGRhMWI4NjRlYQBGAAAAAAAIJ8Vu3g_rSI1rdfqP2WW7BwApi2IKuXg2QJZLIBw8EBXsAAAAAAEMAAApi2IKuXg2QJZLIBw8EBXsAAd_miXDAAA=",
  "receivedDateTime": "2025-09-12T20:49:35Z",
  "subject": "Members caught this 1000% option move",
  "bodyPreview": " \r\n\r\nProfessional Traders. Powerful Profits. Personal Customer Service.\r\n\r\n \r\n\r\nWednesday Sept. 17: we could see the first major rate cut in 4 years. Join Mark and Andrew at 1:45 p.m. to live react to Powell's speech and trade the market aftermath --> ADD",
  "conversationId": "AAQkAGYzNzQ3NThhLWVkOGQtNDJlMC1iYzBkLWFmZGRhMWI4NjRlYQAQAKvBCZpm-OdLivAM9XLIIGM=",
  "sender": {
    "emailAddress": {
      "name": "Mark Sebastian",
      "address": "support@op.optionpit.com"
    }
  },
  "from": {
    "emailAddress": {
      "name": "Mark Sebastian",
      "address": "support@op.optionpit.com"
    }
  },
  "toRecipients": [
    {
      "emailAddress": {
        "name": "Eitan Shamir",
        "address": "eitan@eislaw.co.il"
      }
    }
  ],
  "ccRecipients": [],
  "replyTo": [
    {
      "emailAddress": {
        "name": "Mark Sebastian",
        "address": "support@op.optionpit.com"
      }
    }
  ]
}