{
  "@odata.etag": "W/\"CQAAABYAAAApi2IKuXg2QJZLIBw8EBXsAAdj2USw\"",
  "id": "AAMkAGYzNzQ3NThhLWVkOGQtNDJlMC1iYzBkLWFmZGRhMWI4NjRlYQBGAAAAAAAIJ8Vu3g_rSI1rdfqP2WW7BwApi2IKuXg2QJZLIBw8EBXsAAAAAAFQAAApi2IKuXg2QJZLIBw8EBXsAAdnyvpSAAA=",
  "receivedDateTime": "2025-08-05T12:11:54Z",
  "subject": "Re: Zu Consulting MSA",
  "bodyPreview": "תודה!\r\n\r\n________________________________\r\nFrom: alon harel <alon@eislaw.co.il>\r\nSent: Tuesday, August 5, 2025 1:30:04 PM\r\nTo: Irit Polak <Irit@zu-consulting.com>; Eitan Shamir <eitan@eislaw.co.il>\r\nSubject: Re: Zu Consulting MSA\r\n\r\nהיי אירית.\r\n\r\nאני אעבו",
  "conversationId": "AAQkAGYzNzQ3NThhLWVkOGQtNDJlMC1iYzBkLWFmZGRhMWI4NjRlYQAQAHSoiyDKMUJ4uCz7ZoZBooU=",
  "sender": {
    "emailAddress": {
      "name": "Irit Polak",
      "address": "Irit@zu-consulting.com"
    }
  },
  "from": {
    "emailAddress": {
      "name": "Irit Polak",
      "address": "Irit@zu-consulting.com"
    }
  },
  "toRecipients": [
    {
      "emailAddress": {
        "name": "alon harel",
        "address": "alon@eislaw.co.il"
      }
    },
    {
      "emailAddress": {
        "name": "Eitan Shamir",
        "address": "eitan@eislaw.co.il"
      }
    }
  ],
  "ccRecipients": [],
  "replyTo": []
}