{
  "@odata.etag": "W/\"CQAAABYAAAApi2IKuXg2QJZLIBw8EBXsAAdwZX1x\"",
  "id": "AAMkAGYzNzQ3NThhLWVkOGQtNDJlMC1iYzBkLWFmZGRhMWI4NjRlYQBGAAAAAAAIJ8Vu3g_rSI1rdfqP2WW7BwApi2IKuXg2QJZLIBw8EBXsAAAAAHDsAAApi2IKuXg2QJZLIBw8EBXsAAd0ZIAQAAA=",
  "receivedDateTime": "2025-08-24T11:42:54Z",
  "subject": "מסמך מסוג חשבונית מס קבלה מספר 71075 שהופק עבור ד״ר יהונתן קפלן רפואת עור בע״מ",
  "bodyPreview": "איתן שמיר, חברת עורכי דין\r\n\r\nשלום ד״ר יהונתן קפלן רפואת עור בע״מ ,\r\n\r\nקיבלת חשבונית מס קבלה - 71075\r\n\r\nלצפייה במסמך\r\n\r\nלחיצה על הקישור מהווה הסכמתך\r\nלקבל מסמך חתום דיגיטלית.\r\n\r\n\r\n\r\n\r\n\r\nפגשת פעם מישהו שאוהב ניירת? גם אנחנו לא...\r\n\r\nאין על חשבוניות דיגיטליו",
  "conversationId": "AAQkAGYzNzQ3NThhLWVkOGQtNDJlMC1iYzBkLWFmZGRhMWI4NjRlYQAQAEFrev94bUFKms2FqRcfJ44=",
  "sender": {
    "emailAddress": {
      "name": "notifications@invoice4u.co.il",
      "address": "notifications@invoice4u.co.il"
    }
  },
  "from": {
    "emailAddress": {
      "name": "notifications@invoice4u.co.il",
      "address": "notifications@invoice4u.co.il"
    }
  },
  "toRecipients": [
    {
      "emailAddress": {
        "name": "Eitan Shamir",
        "address": "eitan@eislaw.co.il"
      }
    }
  ],
  "ccRecipients": [],
  "replyTo": []
}