{
  "@odata.etag": "W/\"CQAAABYAAAApi2IKuXg2QJZLIBw8EBXsAAdtm3BC\"",
  "id": "AAMkAGYzNzQ3NThhLWVkOGQtNDJlMC1iYzBkLWFmZGRhMWI4NjRlYQBGAAAAAAAIJ8Vu3g_rSI1rdfqP2WW7BwApi2IKuXg2QJZLIBw8EBXsAAAAAAEJAAApi2IKuXg2QJZLIBw8EBXsAAWOmdtYAAA=",
  "receivedDateTime": "2025-08-20T11:16:00Z",
  "subject": "RE: פנייתך אלינו",
  "bodyPreview": "כתב \"מקובל\" מבחינת הפגישה\r\n\r\n972-52-5903675\r\nעקבו אחרינו באינסטגרם כאן!\r\nמה הלקוחות שלנו חושבים עלינו? ניתן לקרוא כאן, וכן, אנחנו עדיין עם ציון 10 עגול במדרג!\r\nהצטרפו לקהילת בעלי העסקים שלנו בוואטסאפ, כאן!\r\nלהודרת המדריך החינמי שלנו ל-\"חוק הספאם\" לחצו  כא",
  "conversationId": "AAQkAGYzNzQ3NThhLWVkOGQtNDJlMC1iYzBkLWFmZGRhMWI4NjRlYQAQABZZyQJRl0Ogh7cHOlCgfv4=",
  "sender": {
    "emailAddress": {
      "name": "Eitan Shamir",
      "address": "eitan@eislaw.co.il"
    }
  },
  "from": {
    "emailAddress": {
      "name": "Eitan Shamir",
      "address": "eitan@eislaw.co.il"
    }
  },
  "toRecipients": [
    {
      "emailAddress": {
        "name": "Yael Shamir",
        "address": "yael@eislaw.co.il"
      }
    }
  ],
  "ccRecipients": [],
  "replyTo": []
}