{
  "@odata.etag": "W/\"CQAAABYAAAApi2IKuXg2QJZLIBw8EBXsAAcnGJsm\"",
  "id": "AAMkAGYzNzQ3NThhLWVkOGQtNDJlMC1iYzBkLWFmZGRhMWI4NjRlYQBGAAAAAAAIJ8Vu3g_rSI1rdfqP2WW7BwApi2IKuXg2QJZLIBw8EBXsAAAAAAFQAAApi2IKuXg2QJZLIBw8EBXsAAWOmglbAAA=",
  "receivedDateTime": "2025-05-06T15:41:22Z",
  "subject": "Not junk:c34cb964-2c35-4ac6-481b-08dd87b7d394|matan@quicktaxs.com|(Accepted: Matan and Eitan Shamir) 5/6/2025 3:41:19 PM",
  "bodyPreview": "# Questionable URLs detected in message:\r\nNone\r\n\r\n\r\nReceived: from PR3PR01MB6633.eurprd01.prod.exchangelabs.com (::1) by VI1PR01MB6862.eurprd01.prod.exchangelabs.com with HTTPS; Wed, 30 Apr 2025 07:22:57 +0000\r\nReceived: from AS8PR01MB10319.eurprd01.prod.",
  "conversationId": "AAQkAGYzNzQ3NThhLWVkOGQtNDJlMC1iYzBkLWFmZGRhMWI4NjRlYQAQAElPR-WebxpNm_hTHrDbreA=",
  "sender": {
    "emailAddress": {
      "name": "Yael Shamir",
      "address": "yael@eislaw.co.il"
    }
  },
  "from": {
    "emailAddress": {
      "name": "Yael Shamir",
      "address": "yael@eislaw.co.il"
    }
  },
  "toRecipients": [
    {
      "emailAddress": {
        "name": "Eitan Shamir",
        "address": "eitan@eislaw.co.il"
      }
    }
  ],
  "ccRecipients": [],
  "replyTo": []
}