{
  "@odata.etag": "W/\"CQAAABYAAAApi2IKuXg2QJZLIBw8EBXsAAc9dMH9\"",
  "id": "AAMkAGYzNzQ3NThhLWVkOGQtNDJlMC1iYzBkLWFmZGRhMWI4NjRlYQBGAAAAAAAIJ8Vu3g_rSI1rdfqP2WW7BwApi2IKuXg2QJZLIBw8EBXsAAAAAAFQAAApi2IKuXg2QJZLIBw8EBXsAAdBS6_HAAA=",
  "receivedDateTime": "2025-06-11T17:29:34Z",
  "subject": "[Action Advised] Upgrade to the latest Gemini 2.5 Pro Preview model",
  "bodyPreview": "We’ll disable Gemini 2.5 Pro Preview 05-06 on June 19, 2025.\r\n\r\nMY CONSOLE\r\n\r\nHello Eitan,\r\n\r\nWe're writing to inform you that Gemini 2.5 Pro Preview 05-06 for Gemini APIs will be discontinued on June 19, 2025.\r\n\r\nWe have recently launched an updated prev",
  "conversationId": "AAQkAGYzNzQ3NThhLWVkOGQtNDJlMC1iYzBkLWFmZGRhMWI4NjRlYQAQAIGazOvLVMJErQE-PLl_DcU=",
  "sender": {
    "emailAddress": {
      "name": "Google Cloud",
      "address": "CloudPlatform-noreply@google.com"
    }
  },
  "from": {
    "emailAddress": {
      "name": "Google Cloud",
      "address": "CloudPlatform-noreply@google.com"
    }
  },
  "toRecipients": [
    {
      "emailAddress": {
        "name": "Eitan Shamir",
        "address": "eitan@eislaw.co.il"
      }
    }
  ],
  "ccRecipients": [],
  "replyTo": [
    {
      "emailAddress": {
        "name": "Google Cloud",
        "address": "CloudPlatform-noreply@google.com"
      }
    }
  ]
}