{
  "@odata.etag": "W/\"CQAAABYAAAApi2IKuXg2QJZLIBw8EBXsAAeTNbH0\"",
  "id": "AAMkAGYzNzQ3NThhLWVkOGQtNDJlMC1iYzBkLWFmZGRhMWI4NjRlYQBGAAAAAAAIJ8Vu3g_rSI1rdfqP2WW7BwApi2IKuXg2QJZLIBw8EBXsAAAAAAEMAAApi2IKuXg2QJZLIBw8EBXsAAeXVnK8AAA=",
  "receivedDateTime": "2025-10-16T11:18:30Z",
  "subject": "Figma’s CEO: Why AI makes design, craft, and quality the new moat for startups | Dylan Field",
  "bodyPreview": "Figma’s founder on why design is how software wins now, why removing blockers often beats new features, sustaining momentum after 13 years, and how to build taste\r\n͏     ­͏     ­͏     ­͏     ­͏     ­͏     ­͏     ­͏     ­͏     ­͏     ­͏     ­͏     ­͏     ­",
  "conversationId": "AAQkAGYzNzQ3NThhLWVkOGQtNDJlMC1iYzBkLWFmZGRhMWI4NjRlYQAQALqdmA8sgmNEr56eCCPREqs=",
  "sender": {
    "emailAddress": {
      "name": "Lenny's Newsletter",
      "address": "lenny@substack.com"
    }
  },
  "from": {
    "emailAddress": {
      "name": "Lenny's Newsletter",
      "address": "lenny@substack.com"
    }
  },
  "toRecipients": [
    {
      "emailAddress": {
        "name": "Eitan Shamir",
        "address": "eitan@eislaw.co.il"
      }
    }
  ],
  "ccRecipients": [],
  "replyTo": [
    {
      "emailAddress": {
        "name": "Lenny's Newsletter",
        "address": "reply+2wj29m&5kb93z&&cf1c0fe94fcb310d17e5a33f1b256509181b12848c16ab2df912cff9dddb53e0@mg1.substack.com"
      }
    }
  ]
}