{
  "@odata.etag": "W/\"CQAAABYAAAApi2IKuXg2QJZLIBw8EBXsAAdLMmgP\"",
  "id": "AAMkAGYzNzQ3NThhLWVkOGQtNDJlMC1iYzBkLWFmZGRhMWI4NjRlYQBGAAAAAAAIJ8Vu3g_rSI1rdfqP2WW7BwApi2IKuXg2QJZLIBw8EBXsAAAAAAFQAAApi2IKuXg2QJZLIBw8EBXsAAdPEtJHAAA=",
  "receivedDateTime": "2025-06-29T11:07:05Z",
  "subject": "שלחת תשלום אוטומטי אל multiplex",
  "bodyPreview": "איתן שמיר חברת עורכי דין איתן שמיר חברת עורכי דין, הנה הקבלה שלך.\r\nהיי איתן שמיר חברת עורכי דין איתן שמיר חברת עורכי דין,\r\n\r\nתודה על התשלום ל-multiplex\r\n\r\nהנה הפרטים של התשלום האוטומטי שלך עבור .\r\n\r\n________________________________\r\n\r\nפרטים אודות התשלום ש",
  "conversationId": "AAQkAGYzNzQ3NThhLWVkOGQtNDJlMC1iYzBkLWFmZGRhMWI4NjRlYQAQAPkbXg5G2jFKpvn1Jr_JIx8=",
  "sender": {
    "emailAddress": {
      "name": "service@paypal.co.il",
      "address": "service@paypal.co.il"
    }
  },
  "from": {
    "emailAddress": {
      "name": "service@paypal.co.il",
      "address": "service@paypal.co.il"
    }
  },
  "toRecipients": [
    {
      "emailAddress": {
        "name": "Eitan Shamir",
        "address": "eitan@eislaw.co.il"
      }
    }
  ],
  "ccRecipients": [],
  "replyTo": []
}