{
  "@odata.etag": "W/\"CQAAABYAAAApi2IKuXg2QJZLIBw8EBXsAAds8Pdg\"",
  "id": "AAMkAGYzNzQ3NThhLWVkOGQtNDJlMC1iYzBkLWFmZGRhMWI4NjRlYQBGAAAAAAAIJ8Vu3g_rSI1rdfqP2WW7BwApi2IKuXg2QJZLIBw8EBXsAAAAAAFQAAApi2IKuXg2QJZLIBw8EBXsAAWOmf0vAAA=",
  "receivedDateTime": "2025-08-15T08:44:36Z",
  "subject": "From Zero to 1M+ Views: Real Agency Wins on TikTok",
  "bodyPreview": "Hi there\r\n\r\nStill wondering if TikTok works for your clients? Let’s talk real results:\r\n\r\n🟢 Adslab helped a lifestyle brand 4x its conversions through smart creator-led content.\r\n\r\n🟣 Grivety Agency saw a 70% lower CPA for a finance client compared to ot",
  "conversationId": "AAQkAGYzNzQ3NThhLWVkOGQtNDJlMC1iYzBkLWFmZGRhMWI4NjRlYQAQAMMC171cuppLkrPcIKY0SrU=",
  "sender": {
    "emailAddress": {
      "name": "TikTok For Business",
      "address": "news@ads-service.tiktok.com"
    }
  },
  "from": {
    "emailAddress": {
      "name": "TikTok For Business",
      "address": "news@ads-service.tiktok.com"
    }
  },
  "toRecipients": [
    {
      "emailAddress": {
        "name": "Eitan Shamir",
        "address": "eitan@eislaw.co.il"
      }
    }
  ],
  "ccRecipients": [],
  "replyTo": []
}