{
  "@odata.etag": "W/\"CQAAABYAAAApi2IKuXg2QJZLIBw8EBXsAAc3OElV\"",
  "id": "AAMkAGYzNzQ3NThhLWVkOGQtNDJlMC1iYzBkLWFmZGRhMWI4NjRlYQBGAAAAAAAIJ8Vu3g_rSI1rdfqP2WW7BwApi2IKuXg2QJZLIBw8EBXsAAAAAAEMAAApi2IKuXg2QJZLIBw8EBXsAAc7Ck1rAAA=",
  "receivedDateTime": "2025-05-29T17:05:29Z",
  "subject": "Eitan's Calendly updates: May 2025",
  "bodyPreview": "Your time on your terms: New availability features and tips.\r\n͏ ‌     ﻿ ͏ ‌     ﻿ ͏ ‌     ﻿ ͏ ‌     ﻿ ͏ ‌     ﻿ ͏ ‌     ﻿ ͏ ‌     ﻿ ͏ ‌     ﻿ ͏ ‌     ﻿ ͏ ‌     ﻿ ͏ ‌     ﻿ ͏ ‌     ﻿ ͏ ‌     ﻿ ͏ ‌     ﻿ ͏ ‌     ﻿ ͏ ‌     ﻿ ͏ ‌     ﻿ ͏ ‌     ﻿ ͏ ‌     ﻿ ͏ ‌",
  "conversationId": "AAQkAGYzNzQ3NThhLWVkOGQtNDJlMC1iYzBkLWFmZGRhMWI4NjRlYQAQAM9HwySu3QNLnqbxFh9gWT0=",
  "sender": {
    "emailAddress": {
      "name": "Brittany @ Calendly",
      "address": "productupdates@send.calendly.com"
    }
  },
  "from": {
    "emailAddress": {
      "name": "Brittany @ Calendly",
      "address": "productupdates@send.calendly.com"
    }
  },
  "toRecipients": [
    {
      "emailAddress": {
        "name": "Eitan Shamir",
        "address": "eitan@eislaw.co.il"
      }
    }
  ],
  "ccRecipients": [],
  "replyTo": [
    {
      "emailAddress": {
        "name": "teamcalendly@calendly.com",
        "address": "teamcalendly@calendly.com"
      }
    }
  ]
}