{
  "@odata.etag": "W/\"CQAAABYAAAApi2IKuXg2QJZLIBw8EBXsAAeAHM2P\"",
  "id": "AAMkAGYzNzQ3NThhLWVkOGQtNDJlMC1iYzBkLWFmZGRhMWI4NjRlYQBGAAAAAAAIJ8Vu3g_rSI1rdfqP2WW7BwApi2IKuXg2QJZLIBw8EBXsAAAAAAEJAAApi2IKuXg2QJZLIBw8EBXsAAeEKjYyAAA=",
  "receivedDateTime": "2025-09-17T09:05:07Z",
  "subject": "הצעת מחיר והתקדמות - דנה מיכאלי",
  "bodyPreview": "דנה יקרה,\r\n\r\nראשית ברוכה הבאה למשפחת הלקוחות שלי! היה לי עונג להכיר ולשמוע ממך על הדרך המיוחדת שבנית.\r\n\r\nהמטרה שלי בהצעה הזו היא להוריד ממך דאגות, ולתת לך מסגרת משפטית ברורה שתשמור על העסק והמרחב שלך ותאפשר לך להתרחב עסקית בראש שקט ובאינטגריטי מלא מול לקו",
  "conversationId": "AAQkAGYzNzQ3NThhLWVkOGQtNDJlMC1iYzBkLWFmZGRhMWI4NjRlYQAQAFrp6GIP0CxLjQ6agZHB2TY=",
  "sender": {
    "emailAddress": {
      "name": "Eitan Shamir",
      "address": "eitan@eislaw.co.il"
    }
  },
  "from": {
    "emailAddress": {
      "name": "Eitan Shamir",
      "address": "eitan@eislaw.co.il"
    }
  },
  "toRecipients": [
    {
      "emailAddress": {
        "name": "dandi.michaeli@gmail.com",
        "address": "dandi.michaeli@gmail.com"
      }
    }
  ],
  "ccRecipients": [
    {
      "emailAddress": {
        "name": "Yael Shamir",
        "address": "yael@eislaw.co.il"
      }
    }
  ],
  "replyTo": []
}