{
  "@odata.etag": "W/\"CQAAABYAAAApi2IKuXg2QJZLIBw8EBXsAAd2bCls\"",
  "id": "AAMkAGYzNzQ3NThhLWVkOGQtNDJlMC1iYzBkLWFmZGRhMWI4NjRlYQBGAAAAAAAIJ8Vu3g_rSI1rdfqP2WW7BwApi2IKuXg2QJZLIBw8EBXsAAAAAAEMAAApi2IKuXg2QJZLIBw8EBXsAAd6cmzsAAA=",
  "receivedDateTime": "2025-09-03T13:01:59Z",
  "subject": "The MCP Implementation Guide: Solving the 7 Failure Modes that Doom AI Architectures",
  "bodyPreview": "Watch now (16 mins) | The complete guide to avoiding MCP disasters, from the 7 failure modes I've seen in production systems to a 51 page guide covering MCP architectures that actually work in production systems\r\n͏     ­͏     ­͏     ­͏     ­͏     ­͏     ­",
  "conversationId": "AAQkAGYzNzQ3NThhLWVkOGQtNDJlMC1iYzBkLWFmZGRhMWI4NjRlYQAQAEO08NnH9YBDszyrZ0CSWnE=",
  "sender": {
    "emailAddress": {
      "name": "Nate from Nate’s Substack",
      "address": "natesnewsletter@substack.com"
    }
  },
  "from": {
    "emailAddress": {
      "name": "Nate from Nate’s Substack",
      "address": "natesnewsletter@substack.com"
    }
  },
  "toRecipients": [
    {
      "emailAddress": {
        "name": "Eitan Shamir",
        "address": "eitan@eislaw.co.il"
      }
    }
  ],
  "ccRecipients": [],
  "replyTo": [
    {
      "emailAddress": {
        "name": "Nate from Nate’s Substack",
        "address": "reply+2urkrm&5kb93z&&908f545b3678a65d01bb23ca510cbded59c786933cae150e7172acad07361236@mg1.substack.com"
      }
    }
  ]
}