{
  "@odata.etag": "W/\"CQAAABYAAAApi2IKuXg2QJZLIBw8EBXsAAc5KR4x\"",
  "id": "AAMkAGYzNzQ3NThhLWVkOGQtNDJlMC1iYzBkLWFmZGRhMWI4NjRlYQBGAAAAAAAIJ8Vu3g_rSI1rdfqP2WW7BwApi2IKuXg2QJZLIBw8EBXsAAAAAAEMAAApi2IKuXg2QJZLIBw8EBXsAAc8-A3kAAA=",
  "receivedDateTime": "2025-06-03T06:19:00Z",
  "subject": "Your May Search performance for eislaw.co.il",
  "bodyPreview": "New: Click to try\r\n\r\nSearch Console insights\r\n\r\n\r\nYour May performance\r\non Google Search\r\n\r\neislaw.co.il\r\n\r\n96\r\nClicks (web)\r\n\r\n8.85K\r\nImpressions (web)\r\n\r\n36\r\nPages with\r\nfirst impressions\r\n(estimated)\r\n\r\nYour content achievements\r\nTop growing pages\r\nCom",
  "conversationId": "AAQkAGYzNzQ3NThhLWVkOGQtNDJlMC1iYzBkLWFmZGRhMWI4NjRlYQAQAAT0mTGRw5pAiesK8awIEJU=",
  "sender": {
    "emailAddress": {
      "name": "Google Search Console Team",
      "address": "sc-noreply@google.com"
    }
  },
  "from": {
    "emailAddress": {
      "name": "Google Search Console Team",
      "address": "sc-noreply@google.com"
    }
  },
  "toRecipients": [
    {
      "emailAddress": {
        "name": "Eitan Shamir",
        "address": "eitan@eislaw.co.il"
      }
    }
  ],
  "ccRecipients": [],
  "replyTo": [
    {
      "emailAddress": {
        "name": "Google Search Console Team",
        "address": "sc-noreply@google.com"
      }
    }
  ]
}