{
  "@odata.etag": "W/\"CQAAABYAAAApi2IKuXg2QJZLIBw8EBXsAAeJZuHY\"",
  "id": "AAMkAGYzNzQ3NThhLWVkOGQtNDJlMC1iYzBkLWFmZGRhMWI4NjRlYQBGAAAAAAAIJ8Vu3g_rSI1rdfqP2WW7BwApi2IKuXg2QJZLIBw8EBXsAAAAAAEMAAApi2IKuXg2QJZLIBw8EBXsAAeNfMoWAAA=",
  "receivedDateTime": "2025-10-01T20:32:47Z",
  "subject": "How to find profit opportunities? Use this checklist",
  "bodyPreview": " \r\n\r\nProfessional Traders. Powerful Profits. Personal Customer Service.\r\n\r\n \r\n\r\nThe Fed's Rate Cut and the AI Boom have created a HUGE profit opportunity for a custom-built small cap ETF. Click here to gain access!\r\n\r\n \r\nThe biggest question I get from ou",
  "conversationId": "AAQkAGYzNzQ3NThhLWVkOGQtNDJlMC1iYzBkLWFmZGRhMWI4NjRlYQAQAPxz1nt7YmpFsPs6im8HWdE=",
  "sender": {
    "emailAddress": {
      "name": "Frank Gregory",
      "address": "support@op.optionpit.com"
    }
  },
  "from": {
    "emailAddress": {
      "name": "Frank Gregory",
      "address": "support@op.optionpit.com"
    }
  },
  "toRecipients": [
    {
      "emailAddress": {
        "name": "Eitan Shamir",
        "address": "eitan@eislaw.co.il"
      }
    }
  ],
  "ccRecipients": [],
  "replyTo": [
    {
      "emailAddress": {
        "name": "Frank Gregory",
        "address": "support@op.optionpit.com"
      }
    }
  ]
}