{
  "@odata.etag": "W/\"CQAAABYAAAApi2IKuXg2QJZLIBw8EBXsAAc3OD6V\"",
  "id": "AAMkAGYzNzQ3NThhLWVkOGQtNDJlMC1iYzBkLWFmZGRhMWI4NjRlYQBGAAAAAAAIJ8Vu3g_rSI1rdfqP2WW7BwApi2IKuXg2QJZLIBw8EBXsAAAAAAFQAAApi2IKuXg2QJZLIBw8EBXsAAc7Cm48AAA=",
  "receivedDateTime": "2025-05-29T15:35:58Z",
  "subject": "Your invoice is available",
  "bodyPreview": "New invoice has been issued\r\n\r\nThank you for using Mister Horse products. Please, find the attached invoice below.\r\n\r\nPayments are processed automatically. No further action is required.\r\n\r\nSubscription: Yearly\r\nSeats: 1\r\nRenews on: 29 May 2026\r\n\r\nYou can",
  "conversationId": "AAQkAGYzNzQ3NThhLWVkOGQtNDJlMC1iYzBkLWFmZGRhMWI4NjRlYQAQAGGQOkOpnqFKiSdKTFkJcKY=",
  "sender": {
    "emailAddress": {
      "name": "Mister Horse",
      "address": "no-reply@misterhorse.com"
    }
  },
  "from": {
    "emailAddress": {
      "name": "Mister Horse",
      "address": "no-reply@misterhorse.com"
    }
  },
  "toRecipients": [
    {
      "emailAddress": {
        "name": "Eitan Shamir",
        "address": "eitan@eislaw.co.il"
      }
    }
  ],
  "ccRecipients": [],
  "replyTo": []
}