{
  "@odata.etag": "W/\"CQAAABYAAAApi2IKuXg2QJZLIBw8EBXsAAeH0A5M\"",
  "id": "AAMkAGYzNzQ3NThhLWVkOGQtNDJlMC1iYzBkLWFmZGRhMWI4NjRlYQBGAAAAAAAIJ8Vu3g_rSI1rdfqP2WW7BwApi2IKuXg2QJZLIBw8EBXsAAAAAAEKAAApi2IKuXg2QJZLIBw8EBXsAAeL46BOAAA=",
  "receivedDateTime": "2025-09-24T15:28:53Z",
  "subject": "Welcome to Jazz Drum School",
  "bodyPreview": "Dear eitan, welcome!\r\n\r\nThanks so much joining Jazz Drum School! As you explore my courses, please let me know if you have any questions. I'm here to answer your Jazz drumming questions.\r\n\r\nSome suggestions based on your skill level:\r\n\r\n  *   If you're ",
  "conversationId": "AAQkAGYzNzQ3NThhLWVkOGQtNDJlMC1iYzBkLWFmZGRhMWI4NjRlYQAQAPtr3E0WNVxEq4a_rLxwNm4=",
  "sender": {
    "emailAddress": {
      "name": "vonbaron@jazzdrumschool.com",
      "address": "vonbaron@jazzdrumschool.com"
    }
  },
  "from": {
    "emailAddress": {
      "name": "Jazz Drum School",
      "address": "vonbaron@jazzdrumschool.com"
    }
  },
  "toRecipients": [
    {
      "emailAddress": {
        "name": "Eitan Shamir",
        "address": "eitan@eislaw.co.il"
      }
    }
  ],
  "ccRecipients": [],
  "replyTo": [
    {
      "emailAddress": {
        "name": "vonbaron@jazzdrumschool.com",
        "address": "vonbaron@jazzdrumschool.com"
      }
    }
  ]
}