{
  "@odata.type": "#microsoft.graph.eventMessageRequest",
  "@odata.etag": "W/\"CwAAABYAAAApi2IKuXg2QJZLIBw8EBXsAAeAHRBp\"",
  "id": "AAMkAGYzNzQ3NThhLWVkOGQtNDJlMC1iYzBkLWFmZGRhMWI4NjRlYQBGAAAAAAAIJ8Vu3g_rSI1rdfqP2WW7BwApi2IKuXg2QJZLIBw8EBXsAAAAAAEJAAApi2IKuXg2QJZLIBw8EBXsAAeEKjZRAAA=",
  "receivedDateTime": "2025-09-18T16:31:15Z",
  "subject": "זום: איתן עם אירית פולק",
  "bodyPreview": "──────────\r\nEitan Shamir is inviting you to a scheduled Zoom meeting.\r\nJoin Zoom Meeting\r\nhttps://us06web.zoom.us/j/89059772015\r\n\r\nView meeting insights with Zoom AI Companion\r\nhttps://us06web.zoom.us/launch/edl?muid=32d0b015-6a6b-4131-8a11-fb076e0c7241",
  "conversationId": "AAQkAGYzNzQ3NThhLWVkOGQtNDJlMC1iYzBkLWFmZGRhMWI4NjRlYQAQAKIALC6VdCpOu-46JLl1JZU=",
  "sender": {
    "emailAddress": {
      "name": "Eitan Shamir",
      "address": "eitan@eislaw.co.il"
    }
  },
  "from": {
    "emailAddress": {
      "name": "Eitan Shamir",
      "address": "eitan@eislaw.co.il"
    }
  },
  "toRecipients": [
    {
      "emailAddress": {
        "name": "irit",
        "address": "Irit@zu-consulting.com"
      }
    },
    {
      "emailAddress": {
        "name": "alon harel",
        "address": "alon@eislaw.co.il"
      }
    }
  ],
  "ccRecipients": [],
  "replyTo": []
}