{
  "@odata.etag": "W/\"CQAAABYAAAApi2IKuXg2QJZLIBw8EBXsAAdpIfXx\"",
  "id": "AAMkAGYzNzQ3NThhLWVkOGQtNDJlMC1iYzBkLWFmZGRhMWI4NjRlYQBGAAAAAAAIJ8Vu3g_rSI1rdfqP2WW7BwApi2IKuXg2QJZLIBw8EBXsAAAAAAEMAAApi2IKuXg2QJZLIBw8EBXsAAdtGb5gAAA=",
  "receivedDateTime": "2025-08-13T18:59:47Z",
  "subject": "Join Our ClubGPF Live Discussion - August 21, 2025",
  "bodyPreview": "Join Us Next Thursday\r\n\r\n– ClubGPF Live Discussion on Thursday, August 21st –\r\nDear Eitan,\r\n\r\nOur next ClubGPF live discussion will be taking place on Thursday, August 21st at 12pm CT/ 1pm ET US time.\r\n\r\nFor this discussion, GPF Chairman George Friedman w",
  "conversationId": "AAQkAGYzNzQ3NThhLWVkOGQtNDJlMC1iYzBkLWFmZGRhMWI4NjRlYQAQAEFrJDfV7yhGpGHyjjrLD0Q=",
  "sender": {
    "emailAddress": {
      "name": "Geopolitical Futures",
      "address": "support@geopoliticalfutures.com"
    }
  },
  "from": {
    "emailAddress": {
      "name": "Geopolitical Futures",
      "address": "support@geopoliticalfutures.com"
    }
  },
  "toRecipients": [
    {
      "emailAddress": {
        "name": "Eitan Shamir",
        "address": "eitan@eislaw.co.il"
      }
    }
  ],
  "ccRecipients": [],
  "replyTo": [
    {
      "emailAddress": {
        "name": "Geopolitical Futures",
        "address": "support@geopoliticalfutures.com"
      }
    }
  ]
}