{
  "@odata.etag": "W/\"CQAAABYAAAApi2IKuXg2QJZLIBw8EBXsAAeTNa6k\"",
  "id": "AAMkAGYzNzQ3NThhLWVkOGQtNDJlMC1iYzBkLWFmZGRhMWI4NjRlYQBGAAAAAAAIJ8Vu3g_rSI1rdfqP2WW7BwApi2IKuXg2QJZLIBw8EBXsAAAAAAEKAAApi2IKuXg2QJZLIBw8EBXsAAeXVwPuAAA=",
  "receivedDateTime": "2025-10-10T10:41:30Z",
  "subject": "Google Verification Code",
  "bodyPreview": "Google Verification Code\r\n\r\nThis verification code was sent to your email for help getting back into a Google Account:\r\n\r\n730752\r\n\r\nDon’t know why you received this?\r\n\r\nSomeone who couldn’t remember their Google Account details probably gave your email ad",
  "conversationId": "AAQkAGYzNzQ3NThhLWVkOGQtNDJlMC1iYzBkLWFmZGRhMWI4NjRlYQAQAGKgZC2RAh5FtP6uZOgjFl0=",
  "sender": {
    "emailAddress": {
      "name": "Google",
      "address": "noreply@google.com"
    }
  },
  "from": {
    "emailAddress": {
      "name": "Google",
      "address": "noreply@google.com"
    }
  },
  "toRecipients": [
    {
      "emailAddress": {
        "name": "Eitan Shamir",
        "address": "eitan@eislaw.co.il"
      }
    }
  ],
  "ccRecipients": [],
  "replyTo": []
}