{
  "@odata.etag": "W/\"CQAAABYAAAApi2IKuXg2QJZLIBw8EBXsAAd6kIXc\"",
  "id": "AAMkAGYzNzQ3NThhLWVkOGQtNDJlMC1iYzBkLWFmZGRhMWI4NjRlYQBGAAAAAAAIJ8Vu3g_rSI1rdfqP2WW7BwApi2IKuXg2QJZLIBw8EBXsAAAAAAEJAAApi2IKuXg2QJZLIBw8EBXsAAd_mkCKAAA=",
  "receivedDateTime": "2025-09-08T16:26:19Z",
  "subject": "Re: ‏ שירות משפטי - איתן שמיר,  מסמכים והנחיות ליישום והטמעה",
  "bodyPreview": "משפטית כן.\r\n\r\nיש גם חובות טכניות של אבטחת מידע, אבל למאגר המנוהל בידי יחיד (זו ההנחה שליח לגביך) אלה חובות שאתה יכול להסדיר בעצמך. אני אוכל לשלוח לך רשימה של מה צריך.\r\n\r\nאיתן\r\n\r\nFrom: נעם שטרן <noam.stern@gmail.com>\r\nDate: Monday, 8 September 2025 at 9:10",
  "conversationId": "AAQkAGYzNzQ3NThhLWVkOGQtNDJlMC1iYzBkLWFmZGRhMWI4NjRlYQAQABEtgvVZrUhCg8INWnR-BDY=",
  "sender": {
    "emailAddress": {
      "name": "Eitan Shamir",
      "address": "eitan@eislaw.co.il"
    }
  },
  "from": {
    "emailAddress": {
      "name": "Eitan Shamir",
      "address": "eitan@eislaw.co.il"
    }
  },
  "toRecipients": [
    {
      "emailAddress": {
        "name": "נעם שטרן",
        "address": "noam.stern@gmail.com"
      }
    }
  ],
  "ccRecipients": [],
  "replyTo": []
}