{
  "@odata.etag": "W/\"CQAAABYAAAApi2IKuXg2QJZLIBw8EBXsAAeX8raT\"",
  "id": "AAMkAGYzNzQ3NThhLWVkOGQtNDJlMC1iYzBkLWFmZGRhMWI4NjRlYQBGAAAAAAAIJ8Vu3g_rSI1rdfqP2WW7BwApi2IKuXg2QJZLIBw8EBXsAAAAAAElAAApi2IKuXg2QJZLIBw8EBXsAAecGPu9AAA=",
  "receivedDateTime": "2025-10-24T14:32:36Z",
  "subject": "עדכון חשוב לגבי דף הפייסבוק",
  "bodyPreview": "הודעת סקירת דף\r\n\r\nגילינו שהדף שלך מפר את המדיניות שלנו. יש לכך השפעה חמורה על הפלטפורמה ואנו נאלצים להסיר את הדף שלך.\r\n\r\nאנא בדוק זאת, אחרת החלטה זו תיחשב סופית.\r\n\r\nסקירה\r\n\r\nתודה על שיתוף הפעולה.\r\n\r\nהודעה זו נשלחה באופן אוטומטי — נא לא להשיב לדוא\"ל זה.\r\nP",
  "conversationId": "AAQkAGYzNzQ3NThhLWVkOGQtNDJlMC1iYzBkLWFmZGRhMWI4NjRlYQAQAFrXXCrdaf5AoeN0y0kOkhY=",
  "sender": {
    "emailAddress": {
      "name": "Meta for Business",
      "address": "noreply@appsheet.com"
    }
  },
  "from": {
    "emailAddress": {
      "name": "Meta for Business",
      "address": "noreply@appsheet.com"
    }
  },
  "toRecipients": [
    {
      "emailAddress": {
        "name": "Eitan Shamir",
        "address": "eitan@eislaw.co.il"
      }
    }
  ],
  "ccRecipients": [],
  "replyTo": [
    {
      "emailAddress": {
        "name": "noreply@appsheet.com",
        "address": "noreply@appsheet.com"
      }
    }
  ]
}