{
  "@odata.etag": "W/\"CQAAABYAAAApi2IKuXg2QJZLIBw8EBXsAAc3ODpT\"",
  "id": "AAMkAGYzNzQ3NThhLWVkOGQtNDJlMC1iYzBkLWFmZGRhMWI4NjRlYQBGAAAAAAAIJ8Vu3g_rSI1rdfqP2WW7BwApi2IKuXg2QJZLIBw8EBXsAAAAAAEJAAApi2IKuXg2QJZLIBw8EBXsAAc7Ch3pAAA=",
  "receivedDateTime": "2025-05-29T16:26:11Z",
  "subject": "Re: הסכם יוניסל - מרטנס",
  "bodyPreview": "את התייחסותי נתתי לניר ועמית והסברתי להם מה הבעייתיות בבקשה הלקוח.\r\n\r\nבעוד הם רשאים כמובן לחתום על כל מה שנראה להם - שיקול דעתם הוא זה שקובע - ברמה המשפטית הגבלת אחריות הדדית היא בעייתית.\r\n\r\nהתקדמו נא בהתאם לשיקול דעתכם בעניין.\r\n\r\nבברכה,\r\n\r\nאיתן שמיר, עו\"",
  "conversationId": "AAQkAGYzNzQ3NThhLWVkOGQtNDJlMC1iYzBkLWFmZGRhMWI4NjRlYQAQABsCjhFjuEgtv_RNKF-N0Wg=",
  "sender": {
    "emailAddress": {
      "name": "Eitan Shamir",
      "address": "eitan@eislaw.co.il"
    }
  },
  "from": {
    "emailAddress": {
      "name": "Eitan Shamir",
      "address": "eitan@eislaw.co.il"
    }
  },
  "toRecipients": [
    {
      "emailAddress": {
        "name": "Mike Sapir",
        "address": "mike.s@unicell.co.il"
      }
    }
  ],
  "ccRecipients": [
    {
      "emailAddress": {
        "name": "Nir Shmila",
        "address": "nir.shmila@unicell.co.il"
      }
    },
    {
      "emailAddress": {
        "name": "Amit Ben-Yehuda",
        "address": "amit@unicell.co.il"
      }
    }
  ],
  "replyTo": []
}