{
  "@odata.etag": "W/\"CQAAABYAAAApi2IKuXg2QJZLIBw8EBXsAAc9dDO0\"",
  "id": "AAMkAGYzNzQ3NThhLWVkOGQtNDJlMC1iYzBkLWFmZGRhMWI4NjRlYQBGAAAAAAAIJ8Vu3g_rSI1rdfqP2WW7BwApi2IKuXg2QJZLIBw8EBXsAAAAAAEJAAApi2IKuXg2QJZLIBw8EBXsAAdBSaWfAAA=",
  "receivedDateTime": "2025-06-10T14:48:58Z",
  "subject": "Re: ‎⁨עותק הסכם נותן שירותים למורה - לאיתן שמיר⁩",
  "bodyPreview": "הי תדהר,\r\n\r\nעברתי בעיון על המסמך שלך.\r\n\r\nהחלטתי לבסוף לשלוח לך מסמך שלי, שפשוט ערוך טוב יותר.\r\n\r\nאת הסעיפים הספציפיים מהמסמך שלך (תמורה, מגבלת תמורה לחודש, תנאי תשלום, אי תחרות וכיוצ\"ב) הוספתי למסמך שלי עם תיקונים ושינויים כפי שחשבתי שצריך כדי שיהיו אפקטי",
  "conversationId": "AAQkAGYzNzQ3NThhLWVkOGQtNDJlMC1iYzBkLWFmZGRhMWI4NjRlYQAQAG1HCHAUvLRArXYW6U1Ifms=",
  "sender": {
    "emailAddress": {
      "name": "Eitan Shamir",
      "address": "eitan@eislaw.co.il"
    }
  },
  "from": {
    "emailAddress": {
      "name": "Eitan Shamir",
      "address": "eitan@eislaw.co.il"
    }
  },
  "toRecipients": [
    {
      "emailAddress": {
        "name": "Tidhar Maswary",
        "address": "theriderdrums@gmail.com"
      }
    }
  ],
  "ccRecipients": [],
  "replyTo": []
}