{
  "@odata.etag": "W/\"CQAAABYAAAApi2IKuXg2QJZLIBw8EBXsAAeRyJgi\"",
  "id": "AAMkAGYzNzQ3NThhLWVkOGQtNDJlMC1iYzBkLWFmZGRhMWI4NjRlYQBGAAAAAAAIJ8Vu3g_rSI1rdfqP2WW7BwApi2IKuXg2QJZLIBw8EBXsAAAAAAEMAAApi2IKuXg2QJZLIBw8EBXsAAeVEXcgAAA=",
  "receivedDateTime": "2025-10-13T14:32:15Z",
  "subject": "Daily Memo: Hamas Releases Captives, Afghanistan and Pakistan Clash",
  "bodyPreview": "October 13, 2025\r\n\r\nView On Website\r\nOpen as PDF\r\n\r\n\r\nDaily Memo: Hamas Releases Captives, Afghanistan and Pakistan Clash\r\nEfforts toward establishing a sustainable peace in Gaza continue, however.\r\nBy: Geopolitical Futures\r\n\r\nHostages come home. Hamas ha",
  "conversationId": "AAQkAGYzNzQ3NThhLWVkOGQtNDJlMC1iYzBkLWFmZGRhMWI4NjRlYQAQAJuydwyxDKRFukua8I00KO4=",
  "sender": {
    "emailAddress": {
      "name": "Geopolitical Futures",
      "address": "comments@geopoliticalfutures.com"
    }
  },
  "from": {
    "emailAddress": {
      "name": "Geopolitical Futures",
      "address": "comments@geopoliticalfutures.com"
    }
  },
  "toRecipients": [
    {
      "emailAddress": {
        "name": "Eitan Shamir",
        "address": "eitan@eislaw.co.il"
      }
    }
  ],
  "ccRecipients": [],
  "replyTo": [
    {
      "emailAddress": {
        "name": "comments@geopoliticalfutures.com",
        "address": "comments@geopoliticalfutures.com"
      }
    }
  ]
}