{
  "@odata.etag": "W/\"CQAAABYAAAApi2IKuXg2QJZLIBw8EBXsAAeAHQCo\"",
  "id": "AAMkAGYzNzQ3NThhLWVkOGQtNDJlMC1iYzBkLWFmZGRhMWI4NjRlYQBGAAAAAAAIJ8Vu3g_rSI1rdfqP2WW7BwApi2IKuXg2QJZLIBw8EBXsAAAAAAFQAAApi2IKuXg2QJZLIBw8EBXsAAeEKuZpAAA=",
  "receivedDateTime": "2025-09-17T10:10:04Z",
  "subject": "כתבה חדשה של יהושע (ג'וש) בריינר",
  "bodyPreview": "מקורבה של מאי גולן צפוי לחתום על הסכם עד מדינה בתמורה להקלה בעונשו\r\n\r\n\r\n\r\n\r\nיהושע (ג'וש) בריינר\r\n\r\n\r\n\r\nמקורבה של מאי גולן צפוי לחתום על הסכם עד מדינה בתמורה להקלה בעונשו\r\n\r\n\r\n\r\nלהמשך הכתבה\r\n\r\n\r\nכתבות שאולי פספסת\r\n\r\n\r\n\r\nהעדויות מתרבות: הלחץ הנפשי שובר לוחמ",
  "conversationId": "AAQkAGYzNzQ3NThhLWVkOGQtNDJlMC1iYzBkLWFmZGRhMWI4NjRlYQAQAFJnvp6plctDsTSt5ZGd-9Q=",
  "sender": {
    "emailAddress": {
      "name": "הארץ",
      "address": "sysadmin@mc.haaretz.com"
    }
  },
  "from": {
    "emailAddress": {
      "name": "הארץ",
      "address": "sysadmin@mc.haaretz.com"
    }
  },
  "toRecipients": [
    {
      "emailAddress": {
        "name": "Eitan Shamir",
        "address": "eitan@eislaw.co.il"
      }
    }
  ],
  "ccRecipients": [],
  "replyTo": []
}