{
  "@odata.type": "#microsoft.graph.eventMessageRequest",
  "@odata.etag": "W/\"CwAAABYAAAApi2IKuXg2QJZLIBw8EBXsAAc9dDKv\"",
  "id": "AAMkAGYzNzQ3NThhLWVkOGQtNDJlMC1iYzBkLWFmZGRhMWI4NjRlYQBGAAAAAAAIJ8Vu3g_rSI1rdfqP2WW7BwApi2IKuXg2QJZLIBw8EBXsAAAAAAEJAAApi2IKuXg2QJZLIBw8EBXsAAdBSaWdAAA=",
  "receivedDateTime": "2025-06-10T14:20:07Z",
  "subject": "זום ייעוץ מס.1 שירות מנוי: איתן עם עמית גל",
  "bodyPreview": "──────────\r\nEitan Shamir is inviting you to a scheduled Zoom meeting.\r\nJoin Zoom Meeting\r\nhttps://us06web.zoom.us/j/83668963337\r\n\r\nMeeting ID: 836 6896 3337\r\n\r\n---\r\n\r\nOne tap mobile\r\n+13126266799,,83668963337# US (Chicago)\r\n+13462487799,,83668963337# US (",
  "conversationId": "AAQkAGYzNzQ3NThhLWVkOGQtNDJlMC1iYzBkLWFmZGRhMWI4NjRlYQAQAGSz5GD9x7BDsCZq7maCIic=",
  "sender": {
    "emailAddress": {
      "name": "Eitan Shamir",
      "address": "eitan@eislaw.co.il"
    }
  },
  "from": {
    "emailAddress": {
      "name": "Eitan Shamir",
      "address": "eitan@eislaw.co.il"
    }
  },
  "toRecipients": [
    {
      "emailAddress": {
        "name": "עמית גל ויס רויטל אגמי",
        "address": "aghland@gmail.com"
      }
    }
  ],
  "ccRecipients": [],
  "replyTo": []
}