{
  "@odata.etag": "W/\"CQAAABYAAAApi2IKuXg2QJZLIBw8EBXsAAdQa/IA\"",
  "id": "AAMkAGYzNzQ3NThhLWVkOGQtNDJlMC1iYzBkLWFmZGRhMWI4NjRlYQBGAAAAAAAIJ8Vu3g_rSI1rdfqP2WW7BwApi2IKuXg2QJZLIBw8EBXsAAAAAHDsAAApi2IKuXg2QJZLIBw8EBXsAAdUTvy9AAA=",
  "receivedDateTime": "2025-07-07T17:23:21Z",
  "subject": "מסמך מסוג חשבונית מס קבלה מספר 70919 שהופק עבור מור סגמון",
  "bodyPreview": "איתן שמיר, חברת עורכי דין\r\n\r\nשלום מור סגמון,\r\n\r\nקיבלת חשבונית מס קבלה - 70919\r\n\r\nלצפייה במסמך\r\n\r\nלחיצה על הקישור מהווה הסכמתך\r\nלקבל מסמך חתום דיגיטלית.\r\n\r\n\r\n\r\n\r\n\r\nפגשת פעם מישהו שאוהב ניירת? גם אנחנו לא...\r\n\r\nאין על חשבוניות דיגיטליות - הכי קל, נוח וירוק ",
  "conversationId": "AAQkAGYzNzQ3NThhLWVkOGQtNDJlMC1iYzBkLWFmZGRhMWI4NjRlYQAQAOCbrSmxmEFEvbkGxlVKiYk=",
  "sender": {
    "emailAddress": {
      "name": "notifications@invoice4u.co.il",
      "address": "notifications@invoice4u.co.il"
    }
  },
  "from": {
    "emailAddress": {
      "name": "notifications@invoice4u.co.il",
      "address": "notifications@invoice4u.co.il"
    }
  },
  "toRecipients": [
    {
      "emailAddress": {
        "name": "Eitan Shamir",
        "address": "eitan@eislaw.co.il"
      }
    }
  ],
  "ccRecipients": [],
  "replyTo": []
}