{
  "@odata.etag": "W/\"CQAAABYAAAApi2IKuXg2QJZLIBw8EBXsAAdNXxJo\"",
  "id": "AAMkAGYzNzQ3NThhLWVkOGQtNDJlMC1iYzBkLWFmZGRhMWI4NjRlYQBGAAAAAAAIJ8Vu3g_rSI1rdfqP2WW7BwApi2IKuXg2QJZLIBw8EBXsAAAAAAFQAAApi2IKuXg2QJZLIBw8EBXsAAdRQJocAAA=",
  "receivedDateTime": "2025-07-02T06:42:04Z",
  "subject": "Re: חומרים",
  "bodyPreview": "נזכרתי ... יש להוסיף כי זמן שימוש באפליקציית הלימוד והתכנים הלימודיים באתר הינו למשך חצי שנה לאחר מכן יש לשלם 300 שח פלוס מעמ לחודש לשימוש\r\nבברכה\r\nדורון דישבק\r\nנייד: 053-3342218\r\nמייל: dishbak7@gmail.com\r\n\r\n\r\n\r\n‫בתאריך יום א׳, 15 ביוני 2025 ב-21:50 מאת ‪E",
  "conversationId": "AAQkAGYzNzQ3NThhLWVkOGQtNDJlMC1iYzBkLWFmZGRhMWI4NjRlYQAQAGvdfLIqgV9Emb28w17RDD0=",
  "sender": {
    "emailAddress": {
      "name": "דורון יוסף דישבק",
      "address": "dishbak7@gmail.com"
    }
  },
  "from": {
    "emailAddress": {
      "name": "דורון יוסף דישבק",
      "address": "dishbak7@gmail.com"
    }
  },
  "toRecipients": [
    {
      "emailAddress": {
        "name": "Eitan Shamir",
        "address": "eitan@eislaw.co.il"
      }
    }
  ],
  "ccRecipients": [],
  "replyTo": []
}