{
  "@odata.etag": "W/\"CQAAABYAAAApi2IKuXg2QJZLIBw8EBXsAAdEkZcJ\"",
  "id": "AAMkAGYzNzQ3NThhLWVkOGQtNDJlMC1iYzBkLWFmZGRhMWI4NjRlYQBGAAAAAAAIJ8Vu3g_rSI1rdfqP2WW7BwApi2IKuXg2QJZLIBw8EBXsAAAAAAFQAAApi2IKuXg2QJZLIBw8EBXsAAdIbHYFAAA=",
  "receivedDateTime": "2025-06-04T16:38:41Z",
  "subject": "חומרים",
  "bodyPreview": "https://mantaraysailing.co.il/\r\n\r\nכרגע יש לי רק את אפליקציית הלימוד אשר תהיה משולבת בתוך האתר שנמצא בעבודה , אם תרצה להכנס לאפליקציה אתה צריך להרשם כמשתמש חדש , לבחור לעצמך סיסמא ולעדכן אותי שנרשמת כדי לפתוח לך הרשאה לשימוש .\r\n\r\nבברכה\r\nדורון דישבק\r\nנייד: ",
  "conversationId": "AAQkAGYzNzQ3NThhLWVkOGQtNDJlMC1iYzBkLWFmZGRhMWI4NjRlYQAQAGvdfLIqgV9Emb28w17RDD0=",
  "sender": {
    "emailAddress": {
      "name": "דורון יוסף דישבק",
      "address": "dishbak7@gmail.com"
    }
  },
  "from": {
    "emailAddress": {
      "name": "דורון יוסף דישבק",
      "address": "dishbak7@gmail.com"
    }
  },
  "toRecipients": [
    {
      "emailAddress": {
        "name": "Eitan Shamir",
        "address": "eitan@eislaw.co.il"
      }
    }
  ],
  "ccRecipients": [],
  "replyTo": []
}