{
  "@odata.etag": "W/\"CQAAABYAAAApi2IKuXg2QJZLIBw8EBXsAAeIoTx6\"",
  "id": "AAMkAGYzNzQ3NThhLWVkOGQtNDJlMC1iYzBkLWFmZGRhMWI4NjRlYQBGAAAAAAAIJ8Vu3g_rSI1rdfqP2WW7BwApi2IKuXg2QJZLIBw8EBXsAAAAAAElAAApi2IKuXg2QJZLIBw8EBXsAAeMtonTAAA=",
  "receivedDateTime": "2025-09-30T13:23:40Z",
  "subject": "⏰ Son 2 gün: Biletin %40 İndirimli!",
  "bodyPreview": "Sana özel %40 indirimle yurt dışı planı yapıp, rotanı yeni yerlere çevirmenin tam zamanı!\r\nBu e-postayı görüntüleyemiyorsanız tıklayınız.\r\n\r\n\r\n\r\n\r\n\r\n\r\n\r\nSana özel %40 indirimle yurt dışı planı yapıp, rotanı yeni yerlere çevirmenin tam zamanı!\r\n\r\nBiletleri",
  "conversationId": "AAQkAGYzNzQ3NThhLWVkOGQtNDJlMC1iYzBkLWFmZGRhMWI4NjRlYQAQAAZXlaKl2fxNphOXJD9KxnA=",
  "sender": {
    "emailAddress": {
      "name": "Pegasus",
      "address": "pegasus@e-flypgs.com"
    }
  },
  "from": {
    "emailAddress": {
      "name": "Pegasus",
      "address": "pegasus@e-flypgs.com"
    }
  },
  "toRecipients": [
    {
      "emailAddress": {
        "name": "Eitan Shamir",
        "address": "eitan@eislaw.co.il"
      }
    }
  ],
  "ccRecipients": [],
  "replyTo": [
    {
      "emailAddress": {
        "name": "noreply@flypgs.com",
        "address": "noreply@flypgs.com"
      }
    }
  ]
}