{
  "@odata.etag": "W/\"CQAAABYAAAApi2IKuXg2QJZLIBw8EBXsAAeTNa0B\"",
  "id": "AAMkAGYzNzQ3NThhLWVkOGQtNDJlMC1iYzBkLWFmZGRhMWI4NjRlYQBGAAAAAAAIJ8Vu3g_rSI1rdfqP2WW7BwApi2IKuXg2QJZLIBw8EBXsAAAAAAEKAAApi2IKuXg2QJZLIBw8EBXsAAeXVwPDAAA=",
  "receivedDateTime": "2025-10-12T13:46:00Z",
  "subject": "הצעות תוכן שיווקי מבוססות על שיחה עם יש שתי רמות נמוכות יותר מיום 12-10-2025",
  "bodyPreview": "הצעות תוכן שיווקי מבוססות על שיחה עם יש שתי רמות נמוכות יותר מיום 12-10-2025:\n\nבהחלט. פעלתי כמומחה לשיווק ותוכן, ניתחתי את השיחות המעמיקות של עו\"ד איתן שמיר, וזיהיתי ארבעה נושאים בעלי פוטנציאל ויראלי גבוה עבור בעלי עסקים בישראל. כל נושא פותח לכדי סט שלם ש",
  "conversationId": "AAQkAGYzNzQ3NThhLWVkOGQtNDJlMC1iYzBkLWFmZGRhMWI4NjRlYQAQAF8FTFT5ZkhDiSLpL508kpg=",
  "sender": {
    "emailAddress": {
      "name": "Eitan Shamir",
      "address": "eitan@eislaw.co.il"
    }
  },
  "from": {
    "emailAddress": {
      "name": "Eitan Shamir",
      "address": "eitan@eislaw.co.il"
    }
  },
  "toRecipients": [
    {
      "emailAddress": {
        "name": "Eitan Shamir",
        "address": "eitan@eislaw.co.il"
      }
    }
  ],
  "ccRecipients": [],
  "replyTo": []
}