{
  "@odata.etag": "W/\"CQAAABYAAAApi2IKuXg2QJZLIBw8EBXsAAc9dDU/\"",
  "id": "AAMkAGYzNzQ3NThhLWVkOGQtNDJlMC1iYzBkLWFmZGRhMWI4NjRlYQBGAAAAAAAIJ8Vu3g_rSI1rdfqP2WW7BwApi2IKuXg2QJZLIBw8EBXsAAAAAAEJAAApi2IKuXg2QJZLIBw8EBXsAAdBSaWhAAA=",
  "receivedDateTime": "2025-06-10T15:04:28Z",
  "subject": "Re: עדכון תקנון - עומר דפן",
  "bodyPreview": "אכן - לעניין ההסכם הרגיל שלך, שלח לי בוורד.\r\n\r\nאם יש סכסוך ספציפי תמיד שלח לי מסמך חתום ולא את המסמך הסטנדרטי. בכל סכסוך משפטי, צריך לראות מה נחתם בפועל.\r\n\r\nאיתן\r\n\r\n\r\n\r\n\r\n\r\n\r\n\r\n\r\nשריין זמן להיפגש איתי\r\n________________________________\r\nFrom: עומר דפן- מנה",
  "conversationId": "AAQkAGYzNzQ3NThhLWVkOGQtNDJlMC1iYzBkLWFmZGRhMWI4NjRlYQAQAAi0QpVed8RDq25vhzsENNs=",
  "sender": {
    "emailAddress": {
      "name": "Eitan Shamir",
      "address": "eitan@eislaw.co.il"
    }
  },
  "from": {
    "emailAddress": {
      "name": "Eitan Shamir",
      "address": "eitan@eislaw.co.il"
    }
  },
  "toRecipients": [
    {
      "emailAddress": {
        "name": "עומר דפן- מנהל שיווק ומכירות",
        "address": "cmo@omerdaffan.com"
      }
    }
  ],
  "ccRecipients": [],
  "replyTo": []
}