{
  "@odata.etag": "W/\"CQAAABYAAAApi2IKuXg2QJZLIBw8EBXsAAdAupbD\"",
  "id": "AAMkAGYzNzQ3NThhLWVkOGQtNDJlMC1iYzBkLWFmZGRhMWI4NjRlYQBGAAAAAAAIJ8Vu3g_rSI1rdfqP2WW7BwApi2IKuXg2QJZLIBw8EBXsAAAAAAEMAAApi2IKuXg2QJZLIBw8EBXsAAdEkmGBAAA=",
  "receivedDateTime": "2025-06-13T23:23:57Z",
  "subject": "Strategic Projects Under Consideration in Canada",
  "bodyPreview": "June 13, 2025\r\n\r\nView On Website\r\nOpen as PDF\r\n\r\n\r\nStrategic Projects Under Consideration in Canada\r\nOttawa has ambitions to become an energy superpower.\r\nBy: Geopolitical Futures\r\n\r\n(click to enlarge)\r\n\r\nThe Canadian government is making a strong push to",
  "conversationId": "AAQkAGYzNzQ3NThhLWVkOGQtNDJlMC1iYzBkLWFmZGRhMWI4NjRlYQAQAO2wKNZR6bdKjqwx26qZH3c=",
  "sender": {
    "emailAddress": {
      "name": "Geopolitical Futures",
      "address": "comments@geopoliticalfutures.com"
    }
  },
  "from": {
    "emailAddress": {
      "name": "Geopolitical Futures",
      "address": "comments@geopoliticalfutures.com"
    }
  },
  "toRecipients": [
    {
      "emailAddress": {
        "name": "Eitan Shamir",
        "address": "eitan@eislaw.co.il"
      }
    }
  ],
  "ccRecipients": [],
  "replyTo": [
    {
      "emailAddress": {
        "name": "comments@geopoliticalfutures.com",
        "address": "comments@geopoliticalfutures.com"
      }
    }
  ]
}