{
  "@odata.etag": "W/\"CQAAABYAAAApi2IKuXg2QJZLIBw8EBXsAAdEkYlM\"",
  "id": "AAMkAGYzNzQ3NThhLWVkOGQtNDJlMC1iYzBkLWFmZGRhMWI4NjRlYQBGAAAAAAAIJ8Vu3g_rSI1rdfqP2WW7BwApi2IKuXg2QJZLIBw8EBXsAAAxILEJAAApi2IKuXg2QJZLIBw8EBXsAAdIbGmkAAA=",
  "receivedDateTime": "2025-06-18T09:24:37Z",
  "subject": "הצעות תוכן שיווקי מבוססות על שיחה עם יונתן מיום 18-06-2025",
  "bodyPreview": "הצעות תוכן שיווקי מבוססות על שיחה עם יונתן מיום 18-06-2025:\n\nבטח, בשמחה! התמלול הזה עשיר ברעיונות שיכולים להפוך לתכנים שיווקיים מצוינים עבור משרד עורכי דין שרוצה להציג חדשנות ויעילות.\n\nלהלן ארבעה נושאים נבחרים והתכנים עבורם:\n\n* * *\n\n## נושא 1: מהפכת ה-AI ",
  "conversationId": "AAQkAGYzNzQ3NThhLWVkOGQtNDJlMC1iYzBkLWFmZGRhMWI4NjRlYQAQAN_YobiXm6dGs6Fit9R8ua0=",
  "sender": {
    "emailAddress": {
      "name": "Eitan Shamir",
      "address": "eitan@eislaw.co.il"
    }
  },
  "from": {
    "emailAddress": {
      "name": "Eitan Shamir",
      "address": "eitan@eislaw.co.il"
    }
  },
  "toRecipients": [
    {
      "emailAddress": {
        "name": "Eitan Shamir",
        "address": "eitan@eislaw.co.il"
      }
    }
  ],
  "ccRecipients": [],
  "replyTo": []
}