{
  "@odata.etag": "W/\"CQAAABYAAAApi2IKuXg2QJZLIBw8EBXsAAdGR0L5\"",
  "id": "AAMkAGYzNzQ3NThhLWVkOGQtNDJlMC1iYzBkLWFmZGRhMWI4NjRlYQBGAAAAAAAIJ8Vu3g_rSI1rdfqP2WW7BwApi2IKuXg2QJZLIBw8EBXsAAAAAAEMAAApi2IKuXg2QJZLIBw8EBXsAAdKI_kJAAA=",
  "receivedDateTime": "2025-06-21T15:03:25Z",
  "subject": "One goes up, the other goes down",
  "bodyPreview": "Just by looking at one indicator, I’m able to know where the market is moving. ͏  ͏  ͏  ͏  ͏  ͏  ͏  ͏  ͏  ͏  ͏  ͏  ͏  ͏  ͏  ͏  ͏  ͏  ͏  ͏  ͏  ͏  ͏  ͏  ͏  ͏  ͏  ͏  ͏  ͏  ͏  ͏  ͏  ͏  ͏  ͏  ͏  ͏  ͏  ͏  ͏  ͏  ͏  ͏  ͏  ͏  ͏  ͏  ͏  ͏  ͏  ͏  ͏  ͏  ͏  ͏  ͏  ͏  ͏ ",
  "conversationId": "AAQkAGYzNzQ3NThhLWVkOGQtNDJlMC1iYzBkLWFmZGRhMWI4NjRlYQAQAOtfFI3XriBAqAYxPQbPobU=",
  "sender": {
    "emailAddress": {
      "name": "Hannah Selner",
      "address": "support@op.optionpit.com"
    }
  },
  "from": {
    "emailAddress": {
      "name": "Hannah Selner",
      "address": "support@op.optionpit.com"
    }
  },
  "toRecipients": [
    {
      "emailAddress": {
        "name": "Eitan Shamir",
        "address": "eitan@eislaw.co.il"
      }
    }
  ],
  "ccRecipients": [],
  "replyTo": [
    {
      "emailAddress": {
        "name": "Hannah Selner",
        "address": "support@op.optionpit.com"
      }
    }
  ]
}