{
  "@odata.etag": "W/\"CQAAABYAAAApi2IKuXg2QJZLIBw8EBXsAAdNXxl7\"",
  "id": "AAMkAGYzNzQ3NThhLWVkOGQtNDJlMC1iYzBkLWFmZGRhMWI4NjRlYQBGAAAAAAAIJ8Vu3g_rSI1rdfqP2WW7BwApi2IKuXg2QJZLIBw8EBXsAAAAAAFQAAApi2IKuXg2QJZLIBw8EBXsAAdRQJq9AAA=",
  "receivedDateTime": "2025-05-10T10:17:04Z",
  "subject": "Re: משימה - פירוט כרטיסי אשראי",
  "bodyPreview": "מצ״ב חיובים פברואר, מרץ אפריל.\r\nהאמת שאני לא רואה חיובים מיותרים מלבד אולי ביטוח חיים-\r\nרשום שיש 5 חיובים במגדל ועוד שניים במנורה.\r\nמניחה שמגדל זה של כל המשפחה – אם זה אכן ביטוח בריאות, מכבי מספיק. זה מיותר לשלם אקסטרא על הילדים\r\n\r\n--\r\nיעל,\r\nאיתן שמיר חבר",
  "conversationId": "AAQkAGYzNzQ3NThhLWVkOGQtNDJlMC1iYzBkLWFmZGRhMWI4NjRlYQAQANswst2NO6JJhOudXVLpsp4=",
  "sender": {
    "emailAddress": {
      "name": "Yael Shamir",
      "address": "yael@eislaw.co.il"
    }
  },
  "from": {
    "emailAddress": {
      "name": "Yael Shamir",
      "address": "yael@eislaw.co.il"
    }
  },
  "toRecipients": [
    {
      "emailAddress": {
        "name": "Eitan Shamir",
        "address": "eitan@eislaw.co.il"
      }
    }
  ],
  "ccRecipients": [],
  "replyTo": []
}