{
  "@odata.type": "#microsoft.graph.eventMessageRequest",
  "@odata.etag": "W/\"CwAAABYAAAApi2IKuXg2QJZLIBw8EBXsAAdrD3q4\"",
  "id": "AAMkAGYzNzQ3NThhLWVkOGQtNDJlMC1iYzBkLWFmZGRhMWI4NjRlYQBGAAAAAAAIJ8Vu3g_rSI1rdfqP2WW7BwApi2IKuXg2QJZLIBw8EBXsAAAAAAEJAAApi2IKuXg2QJZLIBw8EBXsAAdvCm0RAAA=",
  "receivedDateTime": "2025-08-17T14:42:01Z",
  "subject": "זום: איתן עם דודי מגל",
  "bodyPreview": "──────────\r\nEitan Shamir is inviting you to a scheduled Zoom meeting.\r\nJoin Zoom Meeting\r\nhttps://us06web.zoom.us/j/85610272377\r\n\r\nMeeting ID: 856 1027 2377\r\n\r\n---\r\n\r\nOne tap mobile\r\n+17193594580,,85610272377# US\r\n+17207072699,,85610272377# US (Denver)",
  "conversationId": "AAQkAGYzNzQ3NThhLWVkOGQtNDJlMC1iYzBkLWFmZGRhMWI4NjRlYQAQAKzOWs3jRpRKpQbT_ZQSVmY=",
  "sender": {
    "emailAddress": {
      "name": "Eitan Shamir",
      "address": "eitan@eislaw.co.il"
    }
  },
  "from": {
    "emailAddress": {
      "name": "Eitan Shamir",
      "address": "eitan@eislaw.co.il"
    }
  },
  "toRecipients": [
    {
      "emailAddress": {
        "name": "dudi",
        "address": "dudi@smoove.io"
      }
    }
  ],
  "ccRecipients": [],
  "replyTo": []
}